singletondep/__init__.py
singletondep/errors.py
singletondep/singletondep.py
singletondep/ext/__init__.py
singletondep/ext/fastapi.py
singletondep-0.1.1.dist-info/LICENSE
singletondep-0.1.1.dist-info/METADATA
singletondep-0.1.1.dist-info/WHEEL
singletondep-0.1.1.dist-info/top_level.txt
singletondep-0.1.1.dist-info/RECORD
