Metadata-Version: 2.1
Name: singletondep
Version: 0.1.1
Summary: simple singleton dependency management
Author: Hakan Ozkok
Project-URL: Homepage, https://github.com/hozkok/singletondep
Keywords: singleton,dependency
Classifier: Programming Language :: Python :: 3.10
Classifier: Programming Language :: Python :: 3.11
Requires-Python: >=3.10
License-File: LICENSE
Provides-Extra: fastapi
Requires-Dist: fastapi ; extra == 'fastapi'
Requires-Dist: pydantic ; extra == 'fastapi'
